rrtarget/__init__.py
rrtarget/__version__.py
rrtarget/_api.py
rrtarget/_util.py
rrtarget-0.1.0.dist-info/LICENSE
rrtarget-0.1.0.dist-info/METADATA
rrtarget-0.1.0.dist-info/WHEEL
rrtarget-0.1.0.dist-info/top_level.txt
rrtarget-0.1.0.dist-info/RECORD
