Metadata-Version: 2.1
Name: rrtarget
Version: 0.1.0
Summary: Easily define REST endpoints as first class functions
Home-page: https://github.com/newvicx/rrtarget
Author: Chris Newville
Author-email: chrisnewville1396@gmail.com
License: MIT
Project-URL: Changelog, https://github.com/newvicx/rrtarget/blob/master/CHANGELOG.md
Project-URL: Source, https://github.com/newvicx/rrtarget
Classifier: Development Status :: 4 - Beta
Classifier: Environment :: Web Environment
Classifier: Intended Audience :: Developers
Classifier: License :: OSI Approved :: MIT License
Classifier: Topic :: Internet :: WWW/HTTP
Classifier: Framework :: AsyncIO
Classifier: Programming Language :: Python :: 3
Classifier: Programming Language :: Python :: 3.7
Classifier: Programming Language :: Python :: 3.8
Classifier: Programming Language :: Python :: 3.9
Classifier: Programming Language :: Python :: 3.10
Classifier: Programming Language :: Python :: 3 :: Only
Requires-Python: >=3.7
License-File: LICENSE
Requires-Dist: attrs (>=21.4.0)
Requires-Dist: idna (>=3.3)
Requires-Dist: rfc3986 (>=2.0.0)
